gologin/__init__.py
gologin/_version.py
gologin/golgoin_types.py
gologin/gologin.py
gologin/http_client.py
gologin/py.typed
gologin/browserManager/__init__.py
gologin/browserManager/browserManager.py
gologin/browserManager/languages.py
gologin/cookiesManager/__init__.py
gologin/cookiesManager/cookiesManager.py
gologin/extensionsManager/__init__.py
gologin/extensionsManager/extensionsManager.py
gologin/utils/__init__.py
gologin/utils/sentry_fingerprinting.py
gologin/zero_profile/__init__.py
gologin/zero_profile/bookmarks.py
gologin/zero_profile/preferences.py
gologin-2025.10.24.dist-info/licenses/LICENSE
gologin-2025.10.24.dist-info/METADATA
gologin-2025.10.24.dist-info/WHEEL
gologin-2025.10.24.dist-info/top_level.txt
gologin-2025.10.24.dist-info/RECORD
