Metadata-Version: 2.4
Name: gologin
Version: 2025.10.24
Summary: Official GoLogin python package
Home-page: https://github.com/gologinapp/pygologin
Author: GoLogin
Author-email: yuri@gologin.com
Requires-Python: >=3.5
License-File: LICENSE
Requires-Dist: requests
Requires-Dist: psutil
Requires-Dist: webdriver_manager>=4.0.0
Requires-Dist: selenium>=4.11.0
Requires-Dist: sentry-sdk>=2.29.1
Dynamic: author
Dynamic: author-email
Dynamic: description
Dynamic: description-content-type
Dynamic: home-page
Dynamic: license-file
Dynamic: requires-dist
Dynamic: requires-python
Dynamic: summary
